{
    "base": "Aspb",
    "id": "A00R",
    "mods": [
        {
            "data": 0,
            "id": "aite",
            "type": 0,
            "value": "0",
            "variation": 0
        },
        {
            "data": 0,
            "id": "anam",
            "type": 3,
            "value": "Hidden Spellbook",
            "variation": 0
        },
        {
            "data": 0,
            "id": "ansf",
            "type": 3,
            "value": "(Energy Charge)",
            "variation": 0
        },
        {
            "data": 1,
            "id": "spb1",
            "type": 3,
            "value": "A0BF",
            "variation": 1
        },
        {
            "data": 2,
            "id": "spb2",
            "type": 0,
            "value": "0",
            "variation": 1
        },
        {
            "data": 3,
            "id": "spb3",
            "type": 0,
            "value": "1",
            "variation": 1
        },
        {
            "data": 4,
            "id": "spb4",
            "type": 0,
            "value": "1",
            "variation": 1
        },
        {
            "data": 0,
            "id": "udes",
            "type": 0,
            "value": "0",
            "variation": 0
        }
    ]
}
