{
    "base": "ANre",
    "id": "A09W",
    "mods": [
        {
            "data": 1,
            "id": "Arm1",
            "type": 2,
            "value": 4,
            "variation": 1
        },
        {
            "data": 2,
            "id": "Arm2",
            "type": 0,
            "value": 0,
            "variation": 1
        },
        {
            "data": 0,
            "id": "aare",
            "type": 2,
            "value": 1000,
            "variation": 1
        },
        {
            "data": 0,
            "id": "anam",
            "type": 3,
            "value": "Mana Regen",
            "variation": 0
        },
        {
            "data": 0,
            "id": "ansf",
            "type": 3,
            "value": "(Magical Obelisk - Faerie)",
            "variation": 0
        },
        {
            "data": 0,
            "id": "atar",
            "type": 3,
            "value": "organic,player",
            "variation": 1
        }
    ],
    "type": "Ability"
}
