{
    "base": "ANwk",
    "id": "A0C8",
    "mods": [
        {
            "data": 1,
            "id": "Owk1",
            "type": 2,
            "value": 1.05,
            "variation": 1
        },
        {
            "data": 1,
            "id": "Owk1",
            "type": 2,
            "value": 0.55,
            "variation": 2
        },
        {
            "data": 1,
            "id": "Owk1",
            "type": 2,
            "value": 0.25,
            "variation": 3
        },
        {
            "data": 1,
            "id": "Owk1",
            "type": 2,
            "value": 0.25,
            "variation": 4
        },
        {
            "data": 2,
            "id": "Owk2",
            "type": 2,
            "value": 100000,
            "variation": 1
        },
        {
            "data": 2,
            "id": "Owk2",
            "type": 2,
            "value": 100000,
            "variation": 2
        },
        {
            "data": 2,
            "id": "Owk2",
            "type": 2,
            "value": 100000,
            "variation": 3
        },
        {
            "data": 2,
            "id": "Owk2",
            "type": 2,
            "value": 10,
            "variation": 4
        },
        {
            "data": 3,
            "id": "Owk3",
            "type": 2,
            "value": 100,
            "variation": 1
        },
        {
            "data": 3,
            "id": "Owk3",
            "type": 2,
            "value": 100,
            "variation": 2
        },
        {
            "data": 3,
            "id": "Owk3",
            "type": 2,
            "value": 100,
            "variation": 3
        },
        {
            "data": 3,
            "id": "Owk3",
            "type": 2,
            "value": 100,
            "variation": 4
        },
        {
            "data": 4,
            "id": "Owk4",
            "type": 0,
            "value": 1,
            "variation": 2
        },
        {
            "data": 4,
            "id": "Owk4",
            "type": 0,
            "value": 1,
            "variation": 3
        },
        {
            "data": 4,
            "id": "Owk4",
            "type": 0,
            "value": 1,
            "variation": 4
        },
        {
            "data": 0,
            "id": "aart",
            "type": 3,
            "value": "ReplaceableTextures\\CommandButtons\\BTNLocustSwarm.blp",
            "variation": 0
        },
        {
            "data": 0,
            "id": "abuf",
            "type": 3,
            "value": "BOwk",
            "variation": 2
        },
        {
            "data": 0,
            "id": "abuf",
            "type": 3,
            "value": "BOwk",
            "variation": 3
        },
        {
            "data": 0,
            "id": "abuf",
            "type": 3,
            "value": "BOwk",
            "variation": 4
        },
        {
            "data": 0,
            "id": "acdn",
            "type": 2,
            "value": 55,
            "variation": 1
        },
        {
            "data": 0,
            "id": "acdn",
            "type": 2,
            "value": 50,
            "variation": 2
        },
        {
            "data": 0,
            "id": "acdn",
            "type": 2,
            "value": 45,
            "variation": 3
        },
        {
            "data": 0,
            "id": "acdn",
            "type": 2,
            "value": 40,
            "variation": 4
        },
        {
            "data": 0,
            "id": "achd",
            "type": 0,
            "value": 0,
            "variation": 0
        },
        {
            "data": 0,
            "id": "adur",
            "type": 2,
            "value": 3.1,
            "variation": 1
        },
        {
            "data": 0,
            "id": "adur",
            "type": 2,
            "value": 4.1,
            "variation": 2
        },
        {
            "data": 0,
            "id": "adur",
            "type": 2,
            "value": 5.1,
            "variation": 3
        },
        {
            "data": 0,
            "id": "adur",
            "type": 2,
            "value": 5.1,
            "variation": 4
        },
        {
            "data": 0,
            "id": "aefs",
            "type": 3,
            "value": "ShadowMeld",
            "variation": 0
        },
        {
            "data": 0,
            "id": "ahdu",
            "type": 2,
            "value": 3.1,
            "variation": 1
        },
        {
            "data": 0,
            "id": "ahdu",
            "type": 2,
            "value": 4.1,
            "variation": 2
        },
        {
            "data": 0,
            "id": "ahdu",
            "type": 2,
            "value": 5.1,
            "variation": 3
        },
        {
            "data": 0,
            "id": "ahdu",
            "type": 2,
            "value": 5.1,
            "variation": 4
        },
        {
            "data": 0,
            "id": "aher",
            "type": 0,
            "value": 0,
            "variation": 0
        },
        {
            "data": 0,
            "id": "alev",
            "type": 0,
            "value": 4,
            "variation": 0
        },
        {
            "data": 0,
            "id": "amcs",
            "type": 0,
            "value": 25,
            "variation": 1
        },
        {
            "data": 0,
            "id": "amcs",
            "type": 0,
            "value": 25,
            "variation": 2
        },
        {
            "data": 0,
            "id": "amcs",
            "type": 0,
            "value": 20,
            "variation": 3
        },
        {
            "data": 0,
            "id": "amcs",
            "type": 0,
            "value": 15,
            "variation": 4
        },
        {
            "data": 0,
            "id": "anam",
            "type": 3,
            "value": "Shadow Dash",
            "variation": 0
        },
        {
            "data": 0,
            "id": "ansf",
            "type": 3,
            "value": "(Satyr)",
            "variation": 0
        },
        {
            "data": 0,
            "id": "atp1",
            "type": 3,
            "value": "(|cffffcc00W|r) Shadow Dash - [|cffffcc00Level 1|r]",
            "variation": 1
        },
        {
            "data": 0,
            "id": "atp1",
            "type": 3,
            "value": "(|cffffcc00W|r) Shadow Dash - [|cffffcc00Level 2|r]",
            "variation": 2
        },
        {
            "data": 0,
            "id": "atp1",
            "type": 3,
            "value": "(|cffffcc00W|r) Shadow Dash - [|cffffcc00Level 3|r]",
            "variation": 3
        },
        {
            "data": 0,
            "id": "atp1",
            "type": 3,
            "value": "(|cffffcc00W|r) Shadow Dash - [|cffffcc00Level 4|r]",
            "variation": 4
        },
        {
            "data": 0,
            "id": "aub1",
            "type": 3,
            "value": "The Satyr dashes forward, maximising his movement speed by 3 seconds. If the Satyr attacks during this phase he will deal an extra 100 damage.|n|n|cffadd8e6Cooldown:|r 55",
            "variation": 1
        },
        {
            "data": 0,
            "id": "aub1",
            "type": 3,
            "value": "The Satyr dashes forward, maximising his movement speed by 4 seconds. If the Satyr attacks during this phase he will deal an extra 100 damage.|n|n|cffadd8e6Cooldown:|r 50",
            "variation": 2
        },
        {
            "data": 0,
            "id": "aub1",
            "type": 3,
            "value": "The Satyr dashes forward, maximising his movement speed by 5 seconds. If the Satyr attacks during this phase he will deal an extra 100 damage.|n|n|cffadd8e6Cooldown:|r 45",
            "variation": 3
        },
        {
            "data": 0,
            "id": "aub1",
            "type": 3,
            "value": "The Satyr dashes forward, maximising his movement speed by 5 seconds. If the Satyr attacks during this phase he will deal an extra 100 damage.|n|n|cffadd8e6Cooldown:|r 40",
            "variation": 4
        }
    ],
    "type": "Ability"
}
