{
    "base": "Aspo",
    "id": "A0H7",
    "mods": [
        {
            "data": 1,
            "id": "Spo1",
            "type": 2,
            "value": "0",
            "variation": 1
        },
        {
            "data": 1,
            "id": "Spo1",
            "type": 2,
            "value": "4",
            "variation": 2
        },
        {
            "data": 2,
            "id": "Spo2",
            "type": 2,
            "value": "0.200000003",
            "variation": 1
        },
        {
            "data": 2,
            "id": "Spo2",
            "type": 2,
            "value": "0.300000012",
            "variation": 2
        },
        {
            "data": 3,
            "id": "Spo3",
            "type": 2,
            "value": "0",
            "variation": 1
        },
        {
            "data": 4,
            "id": "Spo4",
            "type": 0,
            "value": "1",
            "variation": 2
        },
        {
            "data": 0,
            "id": "abpx",
            "type": 0,
            "value": "0",
            "variation": 0
        },
        {
            "data": 0,
            "id": "abuf",
            "type": 3,
            "value": "Bspo,Bssd",
            "variation": 2
        },
        {
            "data": 0,
            "id": "achd",
            "type": 0,
            "value": "0",
            "variation": 0
        },
        {
            "data": 0,
            "id": "adur",
            "type": 2,
            "value": "2.5",
            "variation": 1
        },
        {
            "data": 0,
            "id": "adur",
            "type": 2,
            "value": "4",
            "variation": 2
        },
        {
            "data": 0,
            "id": "ahdu",
            "type": 2,
            "value": "2.5",
            "variation": 1
        },
        {
            "data": 0,
            "id": "ahdu",
            "type": 2,
            "value": "4",
            "variation": 2
        },
        {
            "data": 0,
            "id": "alev",
            "type": 0,
            "value": "2",
            "variation": 0
        },
        {
            "data": 0,
            "id": "anam",
            "type": 3,
            "value": "Poisonous Sap",
            "variation": 0
        },
        {
            "data": 0,
            "id": "atar",
            "type": 3,
            "value": "air,ground,organic",
            "variation": 1
        },
        {
            "data": 0,
            "id": "atar",
            "type": 3,
            "value": "air,ground,organic",
            "variation": 2
        },
        {
            "data": 0,
            "id": "atp1",
            "type": 3,
            "value": "Slow Poison",
            "variation": 2
        },
        {
            "data": 0,
            "id": "aub1",
            "type": 3,
            "value": "A poison attack that slows the target enemy's movement by <A0H7,DataB1,%>% for <A0H7,Dur1> seconds.|nPassive.",
            "variation": 1
        },
        {
            "data": 0,
            "id": "aub1",
            "type": 3,
            "value": "A poison attack that slows the target enemy's movement by <A0H7,DataB1,%>% for <A0H7,Dur1> seconds while dealing <A0H7,DataA2> damage per second.|nPassive.",
            "variation": 2
        },
        {
            "data": 0,
            "id": "udes",
            "type": 0,
            "value": "0",
            "variation": 0
        }
    ]
}
