{
    "base": "AIh1",
    "id": "A0K9",
    "mods": [
        {
            "data": 1,
            "id": "Ihpg",
            "type": 0,
            "value": "0",
            "variation": 1
        },
        {
            "data": 0,
            "id": "anam",
            "type": 3,
            "value": "Race Stone Cooldown",
            "variation": 0
        },
        {
            "data": 0,
            "id": "ansf",
            "type": 3,
            "value": "",
            "variation": 0
        }
    ]
}
