{
    "base": "rwiz",
    "id": "I00M",
    "mods": [
        {
            "id": "iabi",
            "type": 3,
            "value": "AIrm,AIbm"
        },
        {
            "id": "icla",
            "type": 3,
            "value": "Artifact"
        },
        {
            "id": "ides",
            "type": 3,
            "value": "|cffdc143cTitan Only|r|cffffd700|n|nArtifact|r"
        },
        {
            "id": "idrp",
            "type": 0,
            "value": "1"
        },
        {
            "id": "igol",
            "type": 0,
            "value": "20"
        },
        {
            "id": "ihtp",
            "type": 0,
            "value": "500000"
        },
        {
            "id": "iico",
            "type": 3,
            "value": "ReplaceableTextures\\CommandButtons\\BTNRune.blp"
        },
        {
            "id": "istr",
            "type": 0,
            "value": "0"
        },
        {
            "id": "uhot",
            "type": 3,
            "value": "S"
        },
        {
            "id": "unam",
            "type": 3,
            "value": "Magic Coral"
        },
        {
            "id": "utip",
            "type": 3,
            "value": "[ |cff3399ffS|r ] Purchase Magic Coral"
        },
        {
            "id": "utub",
            "type": 3,
            "value": "Item attributes:|cfff0f0f0|n|r|cff99b4d1+ 250 mana points|n+ 50% mana regeneration|r"
        }
    ],
    "type": "Item"
}
