{
    "base": "ankh",
    "id": "I00P",
    "mods": [
        {
            "id": "iabi",
            "type": 3,
            "value": "AItn,A012"
        },
        {
            "id": "icla",
            "type": 3,
            "value": "Artifact"
        },
        {
            "id": "ides",
            "type": 3,
            "value": "|cffdc143cTitan Only|r|cffffd700|n|nUnique Artifact|r"
        },
        {
            "id": "igol",
            "type": 0,
            "value": 30
        },
        {
            "id": "ihtp",
            "type": 0,
            "value": 500000
        },
        {
            "id": "istr",
            "type": 0,
            "value": 0
        },
        {
            "id": "uhot",
            "type": 3,
            "value": ""
        },
        {
            "id": "unam",
            "type": 3,
            "value": "|cffffd700Ankh of Reincarnation|r"
        },
        {
            "id": "utip",
            "type": 3,
            "value": ""
        },
        {
            "id": "utub",
            "type": 3,
            "value": "|cfff0e68cYou stumbled upon this ankh on your arrival. Strange power seems to hover around it, protecting its holder - you.|n|r|n|cfff0f0f0Items attributes:|r|n|cff99b4d1+ 10 Attack Damage|r|n|cff3399ffPassive - Undying|r|n|cff99b4d1Upon death, protects the holder, reviving him once with 1200 hit points, consuming this ankh.|r"
        }
    ],
    "type": "Item"
}
