{
    "base": "pnvu",
    "id": "I02Z",
    "mods": [
        {
            "id": "iabi",
            "type": 3,
            "value": ""
        },
        {
            "id": "icla",
            "type": 3,
            "value": "Permanent"
        },
        {
            "id": "ides",
            "type": 3,
            "value": ""
        },
        {
            "id": "idrp",
            "type": 0,
            "value": 1
        },
        {
            "id": "igol",
            "type": 0,
            "value": 0
        },
        {
            "id": "ihtp",
            "type": 0,
            "value": 10
        },
        {
            "id": "iico",
            "type": 3,
            "value": "ReplaceableTextures\\CommandButtons\\BTNSelectHeroOn.blp"
        },
        {
            "id": "ilev",
            "type": 0,
            "value": 0
        },
        {
            "id": "ilvo",
            "type": 0,
            "value": 0
        },
        {
            "id": "ipow",
            "type": 0,
            "value": 1
        },
        {
            "id": "isst",
            "type": 0,
            "value": 0
        },
        {
            "id": "istr",
            "type": 0,
            "value": 0
        },
        {
            "id": "iuse",
            "type": 0,
            "value": 0
        },
        {
            "id": "ubpx",
            "type": 0,
            "value": 2
        },
        {
            "id": "ubpy",
            "type": 0,
            "value": 2
        },
        {
            "id": "uhot",
            "type": 3,
            "value": "C"
        },
        {
            "id": "unam",
            "type": 3,
            "value": "|caa90ee90Randomize Ultimate Tower|r Recipe"
        },
        {
            "id": "utip",
            "type": 3,
            "value": "[ |cff3399ffC|r ] Randomize Ultimate Tower"
        },
        {
            "id": "utub",
            "type": 3,
            "value": "|cfff0f0f0Item attributes:|n|r|cff99b4d1Transmutes one of the ultimate towers you carry into another, random ultimate tower. Make sure you don't carry any ultimate tower you'd like to keep when randomizing.|r|cfff0f0f0|n|r|n|cffffd700Requires:|n|r|cffcd5c5c1 × Any Ultimate Tower|n1 × Titan Egg|r"
        }
    ],
    "type": "Item"
}
